msamdd/__init__.py
msamdd/_optmsa_aff.cp310-win_amd64.pyd
msamdd/_optmsa_cnv.cp310-win_amd64.pyd
msamdd/cli_aff.py
msamdd/cli_cnv.py
msamdd/wrapper_aff.cpp
msamdd/wrapper_cnv.cpp
msamdd-1.4.15.dist-info/licenses/LICENSE
msamdd-1.4.15.dist-info/METADATA
msamdd-1.4.15.dist-info/WHEEL
msamdd-1.4.15.dist-info/entry_points.txt
msamdd-1.4.15.dist-info/top_level.txt
msamdd-1.4.15.dist-info/RECORD
