Metadata-Version: 2.4
Name: msamdd
Version: 1.4.15
Summary: Exact multiple sequence alignment via Synchronized Decision Diagrams
Author: Yeswanth Vootla
Author-email: vootlayeswanth20@gmail.com
License: GPL-2.0-or-later
Requires-Python: >=3.8, <3.13
License-File: LICENSE
Requires-Dist: pybind11>=2.6
Dynamic: author
Dynamic: author-email
Dynamic: description
Dynamic: description-content-type
Dynamic: license
Dynamic: license-file
Dynamic: requires-dist
Dynamic: requires-python
Dynamic: summary
